design.sv
// Code your design here
module MIPS32_pipe(input clk1, clk2);
  
  reg [31:0] PC, IF_ID_IR, IF_ID_NPC;		// ouput of IF_ID piplined stage
  reg [31:0] ID_EX_IR, ID_EX_NPC, ID_EX_A, ID_EX_B, ID_EX_Imm; //output of ID_EX piplined stage
  reg [2:0] ID_EX_type, EX_MEM_type, MEM_WB_type;	// reg for knowing the type of cmd
  reg [31:0] EX_MEM_IR, EX_MEM_ALUout, EX_MEM_B;
  reg EX_MEM_cond;  
  reg [31:0] MEM_WB_IR, MEM_WB_ALUout, MEM_WB_LMD;	// ouput of MEM_WB piplined stage
  
  reg [31:0] RegFile [0:31];	// Reg Bank of size 32x32
  reg [31:0] Memory [0:1023];	// Memory of size 1024x32
  
  parameter ADD=6'b000000, SUB=6'b000001, AND=6'b000010, OR=6'b000011, SLT=6'b000100, MUL=6'b00101, HLT=6'b111111, LW=6'b001000, SW=6'b001001, ADDI=6'b001010, SUBI=6'b001011, SLTI=6'b001100, BNEQZ=6'b001101, BEQZ=6'b001110;	// parameters for operations of ALU making it easier to read
  
  parameter RR_ALU=3'b000, RM_ALU=3'b001, LOAD=3'b010, STORE=3'b011, BRANCH=3'b100, HALT=3'b101;	// different types of cmd
  
  reg HALTED;	// set to 1 when HLT inst is detected at WB stage
  reg TAKEN_BRANCH; 	// tells whether it is Branch inst to disable following inst
  
  always @ (posedge clk1)		// IF stage
    if(HALTED == 0)
      begin
        if(((EX_MEM_IR[31:26] == BEQZ) && (EX_MEM_cond == 1)) || ((EX_MEM_IR[31:26] == BNEQZ) && (EX_MEM_cond == 0)))		// If branching is true
          begin
            IF_ID_IR <= #2 Memory[EX_MEM_ALUout];		// Next inst memory address must be fetched from address calculated in MEM stage 
            TAKEN_BRANCH <= #2 1'b1;
            IF_ID_NPC <= #2 EX_MEM_ALUout + 1;
            PC <= #2 EX_MEM_ALUout + 1;
          end
        else
          begin
            IF_ID_IR <= #2 Memory[PC];		// Else execute next PC
            IF_ID_NPC <= #2 PC + 1;
            PC <= #2 PC + 1;
          end
      end
  
  always @ (posedge clk2)		// ID stage
    if(HALTED == 0)
      begin
        if(IF_ID_IR[25:21] == 5'b00000) ID_EX_A <= 0;
        else ID_EX_A <= #2 RegFile[IF_ID_IR[25:21]];		// rs
          
        if(IF_ID_IR[20:16] == 5'b00000) ID_EX_B <= 0;
        else ID_EX_B <= #2 RegFile[IF_ID_IR[20:16]];		//rt
        
        ID_EX_NPC <= #2 IF_ID_NPC;
        ID_EX_IR <= #2 IF_ID_IR;
        ID_EX_Imm <= #2 {{16{IF_ID_IR[15]}},IF_ID_IR[15:0]};	// sign extenision of 16 bit immediate
        
        case(IF_ID_IR[31:26])
          ADD, SUB, AND, OR, SLT, MUL: ID_EX_type <= #2 RR_ALU;
          ADDI, SUBI, SLTI: ID_EX_type <= #2 RM_ALU;
          LW: ID_EX_type <= #2 LOAD;
          SW: ID_EX_type <= #2 STORE;
          BEQZ, BNEQZ: ID_EX_type <= #2 BRANCH;
          HLT: ID_EX_type <= #2 HALT;
          default: ID_EX_type <= #2 HALT;
        endcase
      end
  
  always @ (posedge clk1)		// EX
    if(HALTED == 0)
      begin
        EX_MEM_type <= #2 ID_EX_type;
        EX_MEM_IR <= #2 ID_EX_IR;
        TAKEN_BRANCH <= #2 1'b0;
        
        case(ID_EX_type)
          RR_ALU: begin
            		case(ID_EX_IR[31:26])
                      ADD: EX_MEM_ALUout <= #2 ID_EX_A + ID_EX_B;
                      SUB: EX_MEM_ALUout <= #2 ID_EX_A - ID_EX_B;
                      AND: EX_MEM_ALUout <= #2 ID_EX_A & ID_EX_B;
                      OR: EX_MEM_ALUout <= #2 ID_EX_A | ID_EX_B;
                      SLT: EX_MEM_ALUout <= #2 ID_EX_A < ID_EX_B;
                      MUL: EX_MEM_ALUout <= #2 ID_EX_A * ID_EX_B;
                      default : EX_MEM_ALUout <= #2 32'hxxxx_xxxx;
                    endcase
                  end
          
          RM_ALU: begin
            case(ID_EX_IR[31:26])
              ADDI: EX_MEM_ALUout <= #2 ID_EX_A + ID_EX_Imm;
              SUBI: EX_MEM_ALUout <= #2 ID_EX_A - ID_EX_Imm;
              SLTI: EX_MEM_ALUout <= #2 ID_EX_A < ID_EX_Imm;
              default: EX_MEM_ALUout <= #2 32'hxxxx_xxxx;
            endcase
          end
          
          LOAD, STORE: begin
            EX_MEM_ALUout <= #2 ID_EX_A + ID_EX_Imm;
            EX_MEM_B <= #2 ID_EX_B;
          end
          
          BRANCH: begin
            EX_MEM_ALUout <= #2 ID_EX_NPC + ID_EX_Imm;
            EX_MEM_cond <= #2 (ID_EX_A == 0);
          end
          
        endcase
      end
  
  always @ (posedge clk2)		// MEM
    if(HALTED == 0)
      begin
        MEM_WB_type <= #2 EX_MEM_type;
        MEM_WB_IR <= #2 EX_MEM_IR;
        
        case(EX_MEM_type)
          RR_ALU, RM_ALU: MEM_WB_ALUout <= #2 EX_MEM_ALUout;
          LOAD: MEM_WB_LMD <= #2 Memory[EX_MEM_ALUout];
          STORE: if(TAKEN_BRANCH == 0)		// Disable write if inst is Branch 
            		Memory[EX_MEM_ALUout] <= #2 EX_MEM_B;
        endcase
      end
  
  always @ (posedge clk1)		// WB
    begin
      if(TAKEN_BRANCH == 0)
        case(MEM_WB_type)
          RR_ALU: RegFile[MEM_WB_IR[15:11]] <= #2 MEM_WB_ALUout;
          RM_ALU: RegFile[MEM_WB_IR[20:16]] <= #2 MEM_WB_ALUout;
          LOAD: RegFile[MEM_WB_IR[20:16]] <= #2 MEM_WB_LMD;
          HALT: HALTED <= 1'b1;
        endcase
    end
  
endmodule

testbench.sv
// Code your testbench here
// or browse Examples

// testbench to add 2 numbers in a microprocessor
/*
module t_MIPS;
  reg clk1, clk2;
  integer k;
  
  MIPS32_pipe MUT(clk1, clk2);
  
  initial 
    begin
      clk1 = 0; clk2 = 0;
      repeat(20)
        begin
          #5 clk1 = 1; #5 clk1 = 0;
          #5 clk2 = 1; #5 clk2 = 0;
        end
    end
  
  initial 
    begin
      for(k=0; k<31; k = k+1)
        MUT.RegFile[k] = k;
      
      MUT.Memory[0] = 32'h2401_000a;	// ADDI R1,R0,10
      MUT.Memory[1] = 32'h2402_0014;	// ADDI R2,R0,20
      MUT.Memory[2] = 32'h2403_0019;	// ADDI R3,R0,30
      MUT.Memory[3] = 32'h0ce7_7800;	// OR R7,R7,R7 - Dummy Inst
      MUT.Memory[4] = 32'h0ce7_7800;	// OR R7,R7,R7 - Dummy Inst
      MUT.Memory[5] = 32'h0022_2000;	// ADD R4,R2,R1
      MUT.Memory[6] = 32'h0ce7_7800;	// OR R7,R7,R7 - Dummy Inst
      MUT.Memory[7] = 32'h0083_2800;	// ADD R5,R4,R3
      MUT.Memory[8] = 32'hfc00_0000;	// HLT
      
      MUT.HALTED = 0;
      MUT.TAKEN_BRANCH = 0;
      MUT.PC = 0;
      
      #280
      for(k=0; k<6; k = k+1)
        $display("R%1d - %2d", k, MUT.RegFile[k]);
    end
  
  initial
    begin
      $dumpfile("MIPS.vcd");
      $dumpvars(0,t_MIPS);
      #300 $finish;
    end
  
endmodule
*/

// testbench for factorial
/*
module t_MIPS;
  reg clk1, clk2;
  integer k;
  
  MIPS32_pipe MUT(clk1, clk2);
  
  initial 
    begin
      clk1 = 0; clk2 = 0;
      repeat(200)
        begin
          #5 clk1 = 1; #5 clk1 = 0;
          #5 clk2 = 1; #5 clk2 = 0;
        end
    end
  
  initial 
    begin
      
      MUT.Memory[0] = 32'h280a_00c8;	// ADDI R10,R0,200
      MUT.Memory[1] = 32'h2802_0001;	// ADDI R2,R0,1
      MUT.Memory[2] = 32'h0ce7_7800;	// OR R7,R7,R7 - Dummy Inst
      MUT.Memory[3] = 32'h2143_0000;	// LW R3,0(R10)
      MUT.Memory[4] = 32'h0ce7_7800;	// OR R7,R7,R7 - Dummy Inst
      MUT.Memory[5] = 32'h1443_1000;	// Loop: MUL R2,R2,R3
      MUT.Memory[6] = 32'h2c63_0001;	// SUBI R3,R3,1
      MUT.Memory[7] = 32'h0ce7_7800;	// OR R7,R7,R7 - Dummy Inst
      MUT.Memory[8] = 32'h3460_fffc;	// BNEQZ R3,Loop
      MUT.Memory[9] = 32'h2542_fffe;	// SW R2,-2(R10)
      MUT.Memory[10] = 32'hfc00_0000;	// HLT
      
      MUT.Memory[200] = 6;	// Put the number of which you want to find factorial 
      MUT.HALTED = 0;
      MUT.TAKEN_BRANCH = 0;
      MUT.PC = 0;
      
      #2000
      $display("Mem[200] = %2d, Mem[198] = %6d", MUT.Memory[200], MUT.Memory[198]);
    end
  
  initial
    begin
      $dumpfile("MIPS.vcd");
      $dumpvars(0,t_MIPS);
      $monitor("R2: %4d, R3: %1d", MUT.RegFile[2], MUT.RegFile[3]);
      #3000 $finish;
    end
  
endmodule
*/

// testbench to find nth Fibonacci number
module t_MIPS;
  reg clk1, clk2;
  integer k;
  
  MIPS32_pipe MUT(clk1, clk2);
  
  initial 
    begin
      clk1 = 0; clk2 = 0;
      repeat(200)
        begin
          #5 clk1 = 1; #5 clk1 = 0;
          #5 clk2 = 1; #5 clk2 = 0;
        end
    end
  
  initial 
    begin
      
      MUT.Memory[0] = 32'h2809_00c8;	// ADDI R9,R0,200
      MUT.Memory[1] = 32'h0000_0800;	// ADD R1,R0,R0
      MUT.Memory[2] = 32'h2802_0001;	// ADDI R2,R0,1
      MUT.Memory[3] = 32'h212a_0000;	// LW R10,0(R9)
      MUT.Memory[4] = 32'h0ce7_7800;	// OR R7,R7,R7 - Dummy Inst
      MUT.Memory[5] = 32'h0ce7_7800;	// OR R7,R7,R7 - Dummy Inst
      MUT.Memory[6] = 32'h2d4a_0002;	// SUBI R10,R10,2
      MUT.Memory[7] = 32'h0022_1800;	// Loop: ADD R3,R1,R2
      MUT.Memory[8] = 32'h0040_0800;	// ADD R1,R2,R0
      MUT.Memory[9] = 32'h0060_1000;	// ADD R2,R3,R0
      MUT.Memory[10] = 32'h2d4a_0001;	// SUBI R10,R10,1
      MUT.Memory[11] = 32'h0ce7_7800;	// OR R7,R7,R7 - Dummy Inst
      MUT.Memory[12] = 32'h0ce7_7800;	// OR R7,R7,R7 - Dummy Inst
      MUT.Memory[13] = 32'h3540_fff9;	// BNEQZ R10,Loop(-7)
      MUT.Memory[14] = 32'h2523_fffe;	// SW R3,-2(R9)
      MUT.Memory[15] = 32'hfc00_0000;	// HLT
      
      MUT.Memory[200] = 10;	// Put the n value  
      MUT.HALTED = 0;
      MUT.TAKEN_BRANCH = 0;
      MUT.PC = 0;
      
      #2000
      $display("Mem[200] = %2d, Mem[198] = %6d", MUT.Memory[200], MUT.Memory[198]);
    end
  
  initial
    begin
      $dumpfile("MIPS.vcd");
      $dumpvars(0,t_MIPS);
      $monitor("R1: %2d, R2: %2d, R3: %2d, R10: %2d", MUT.RegFile[1], MUT.RegFile[2], MUT.RegFile[3], MUT.RegFile[10]);
      #3000 $finish;
    end
  
endmodule

MIPS.vcd
$date
	Mon Aug 10 19:20:57 2020
$end
$version
	Icarus Verilog
$end
$timescale
	1s
$end
$scope module t_MIPS $end
$var reg 1 ! clk1 $end
$var reg 1 " clk2 $end
$scope module MUT $end
$var wire 1 # clk1 $end
$var wire 1 $ clk2 $end
$var reg 32 % EX_MEM_ALUout [31:0] $end
$var reg 32 & EX_MEM_B [31:0] $end
$var reg 32 ' EX_MEM_IR [31:0] $end
$var reg 1 ( EX_MEM_cond $end
$var reg 3 ) EX_MEM_type [2:0] $end
$var reg 1 * HALTED $end
$var reg 32 + ID_EX_A [31:0] $end
$var reg 32 , ID_EX_B [31:0] $end
$var reg 32 - ID_EX_IR [31:0] $end
$var reg 32 . ID_EX_Imm [31:0] $end
$var reg 32 / ID_EX_NPC [31:0] $end
$var reg 3 0 ID_EX_type [2:0] $end
$var reg 32 1 IF_ID_IR [31:0] $end
$var reg 32 2 IF_ID_NPC [31:0] $end
$var reg 32 3 MEM_WB_ALUout [31:0] $end
$var reg 32 4 MEM_WB_IR [31:0] $end
$var reg 32 5 MEM_WB_LMD [31:0] $end
$var reg 3 6 MEM_WB_type [2:0] $end
$var reg 32 7 PC [31:0] $end
$var reg 1 8 TAKEN_BRANCH $end
$upscope $end
$upscope $end
$enddefinitions $end
#0
$dumpvars
08
b0 7
bx 6
bx 5
bx 4
bx 3
bx 2
bx 1
bx 0
bx /
bx .
bx -
bx ,
bx +
0*
bx )
x(
bx '
bx &
bx %
0$
0#
0"
0!
$end
#5
1!
1#
#7
b1 7
b1 2
b101000000010010000000011001000 1
#10
0!
0#
#15
b0 +
1"
1$
#17
b1 0
b11001000 .
b101000000010010000000011001000 -
b1 /
#20
0"
0$
#25
1!
1#
#27
b11001000 %
b101000000010010000000011001000 '
b1 )
b10 7
b10 2
b100000000000 1
#30
0!
0#
#35
b0 ,
1"
1$
#37
b11001000 3
b101000000010010000000011001000 4
b1 6
b0 0
b100000000000 .
b100000000000 -
b10 /
#40
0"
0$
#45
1!
1#
#47
b11 7
b11 2
b101000000000100000000000000001 1
b0 %
b100000000000 '
b0 )
#50
0!
0#
#55
1"
1$
#57
b1 0
b1 .
b101000000000100000000000000001 -
b11 /
bx ,
b0 3
b100000000000 4
b0 6
#60
0"
0$
#65
1!
1#
#67
b1 %
b101000000000100000000000000001 '
b1 )
b100 7
b100 2
b100001001010100000000000000000 1
#70
0!
0#
#75
1"
1$
#77
b1 3
b101000000000100000000000000001 4
b1 6
b10 0
b0 .
b100001001010100000000000000000 -
b100 /
b11001000 +
#80
0"
0$
#85
1!
1#
#87
b101 7
b101 2
b1100111001110111100000000000 1
b11001000 %
b100001001010100000000000000000 '
b10 )
#90
0!
0#
#95
1"
1$
#97
b0 0
b111100000000000 .
b1100111001110111100000000000 -
b101 /
bx +
b1010 5
b100001001010100000000000000000 4
b10 6
#100
0"
0$
#105
1!
1#
#107
bx %
b1100111001110111100000000000 '
b0 )
b110 7
b110 2
#110
0!
0#
#115
1"
1$
#117
bx 3
b1100111001110111100000000000 4
b0 6
b110 /
#120
0"
0$
#125
1!
1#
#127
b111 7
b111 2
b101101010010100000000000000010 1
#130
0!
0#
#135
1"
1$
#137
b1 0
b10 .
b101101010010100000000000000010 -
b111 /
b1010 ,
b1010 +
#140
0"
0$
#145
1!
1#
#147
b1000 %
b101101010010100000000000000010 '
b1 )
b1000 7
b1000 2
b1000100001100000000000 1
#150
0!
0#
#155
1"
1$
#157
b1000 3
b101101010010100000000000000010 4
b1 6
b0 0
b1100000000000 .
b1000100001100000000000 -
b1000 /
b1 ,
b0 +
#160
0"
0$
#165
1!
1#
#167
b1001 7
b1001 2
b10000000000100000000000 1
b1 %
b1000100001100000000000 '
b0 )
#170
0!
0#
#175
b0 ,
1"
1$
#177
b100000000000 .
b10000000000100000000000 -
b1001 /
b1 +
b1 3
b1000100001100000000000 4
b0 6
#180
0"
0$
#185
1!
1#
#187
b10000000000100000000000 '
b1010 7
b1010 2
b11000000001000000000000 1
#190
0!
0#
#195
1"
1$
#197
b10000000000100000000000 4
b1000000000000 .
b11000000001000000000000 -
b1010 /
#200
0"
0$
#205
1!
1#
#207
b1011 7
b1011 2
b101101010010100000000000000001 1
b11000000001000000000000 '
#210
0!
0#
#215
1"
1$
#217
b1 0
b1 .
b101101010010100000000000000001 -
b1011 /
b1000 ,
b1000 +
b11000000001000000000000 4
#220
0"
0$
#225
1!
1#
#227
b111 %
b101101010010100000000000000001 '
b1 )
b1100 7
b1100 2
b1100111001110111100000000000 1
#230
0!
0#
#235
1"
1$
#237
b111 3
b101101010010100000000000000001 4
b1 6
b0 0
b111100000000000 .
b1100111001110111100000000000 -
b1100 /
bx ,
bx +
#240
0"
0$
#245
1!
1#
#247
b1101 7
b1101 2
bx %
b1100111001110111100000000000 '
b0 )
#250
0!
0#
#255
1"
1$
#257
b1101 /
bx 3
b1100111001110111100000000000 4
b0 6
#260
0"
0$
#265
1!
1#
#267
b1110 7
b1110 2
b110101010000001111111111111001 1
#270
0!
0#
#275
b0 ,
1"
1$
#277
b100 0
b11111111111111111111111111111001 .
b110101010000001111111111111001 -
b1110 /
b111 +
#280
0"
0$
#285
1!
1#
#287
b1111 7
b1111 2
b100101001000111111111111111110 1
0(
b111 %
b110101010000001111111111111001 '
b100 )
#290
0!
0#
#295
1"
1$
#297
b11 0
b11111111111111111111111111111110 .
b100101001000111111111111111110 -
b1111 /
b1 ,
b11001000 +
b110101010000001111111111111001 4
b100 6
#300
0"
0$
#305
1!
1#
#307
b1 &
b11000110 %
b100101001000111111111111111110 '
b11 )
b1000 7
b1000 2
08
b1000100001100000000000 1
#310
0!
0#
#315
1"
1$
#317
b100101001000111111111111111110 4
b11 6
b0 0
b1100000000000 .
b1000100001100000000000 -
b1000 /
b1 +
#320
0"
0$
#325
1!
1#
#327
b1001 7
b1001 2
b10000000000100000000000 1
b10 %
b1000100001100000000000 '
b0 )
#330
0!
0#
#335
b0 ,
1"
1$
#337
b100000000000 .
b10000000000100000000000 -
b1001 /
b10 3
b1000100001100000000000 4
b0 6
#340
0"
0$
#345
1!
1#
#347
b1 %
b10000000000100000000000 '
b1010 7
b1010 2
b11000000001000000000000 1
#350
0!
0#
#355
1"
1$
#357
b1 3
b10000000000100000000000 4
b1000000000000 .
b11000000001000000000000 -
b1010 /
b10 +
#360
0"
0$
#365
1!
1#
#367
b1011 7
b1011 2
b101101010010100000000000000001 1
b10 %
b11000000001000000000000 '
#370
0!
0#
#375
1"
1$
#377
b1 0
b1 .
b101101010010100000000000000001 -
b1011 /
b111 ,
b111 +
b10 3
b11000000001000000000000 4
#380
0"
0$
#385
1!
1#
#387
b110 %
b101101010010100000000000000001 '
b1 )
b1100 7
b1100 2
b1100111001110111100000000000 1
#390
0!
0#
#395
1"
1$
#397
b110 3
b101101010010100000000000000001 4
b1 6
b0 0
b111100000000000 .
b1100111001110111100000000000 -
b1100 /
bx ,
bx +
#400
0"
0$
#405
1!
1#
#407
b1101 7
b1101 2
bx %
b1100111001110111100000000000 '
b0 )
#410
0!
0#
#415
1"
1$
#417
b1101 /
bx 3
b1100111001110111100000000000 4
b0 6
#420
0"
0$
#425
1!
1#
#427
b1110 7
b1110 2
b110101010000001111111111111001 1
#430
0!
0#
#435
b0 ,
1"
1$
#437
b100 0
b11111111111111111111111111111001 .
b110101010000001111111111111001 -
b1110 /
b110 +
#440
0"
0$
#445
1!
1#
#447
b1111 7
b1111 2
b100101001000111111111111111110 1
b111 %
b110101010000001111111111111001 '
b100 )
#450
0!
0#
#455
1"
1$
#457
b11 0
b11111111111111111111111111111110 .
b100101001000111111111111111110 -
b1111 /
b10 ,
b11001000 +
b110101010000001111111111111001 4
b100 6
#460
0"
0$
#465
1!
1#
#467
b10 &
b11000110 %
b100101001000111111111111111110 '
b11 )
b1000 7
b1000 2
08
b1000100001100000000000 1
#470
0!
0#
#475
1"
1$
#477
b100101001000111111111111111110 4
b11 6
b0 0
b1100000000000 .
b1000100001100000000000 -
b1000 /
b1 +
#480
0"
0$
#485
1!
1#
#487
b1001 7
b1001 2
b10000000000100000000000 1
b11 %
b1000100001100000000000 '
b0 )
#490
0!
0#
#495
b0 ,
1"
1$
#497
b100000000000 .
b10000000000100000000000 -
b1001 /
b10 +
b11 3
b1000100001100000000000 4
b0 6
#500
0"
0$
#505
1!
1#
#507
b10 %
b10000000000100000000000 '
b1010 7
b1010 2
b11000000001000000000000 1
#510
0!
0#
#515
1"
1$
#517
b10 3
b10000000000100000000000 4
b1000000000000 .
b11000000001000000000000 -
b1010 /
b11 +
#520
0"
0$
#525
1!
1#
#527
b1011 7
b1011 2
b101101010010100000000000000001 1
b11 %
b11000000001000000000000 '
#530
0!
0#
#535
1"
1$
#537
b1 0
b1 .
b101101010010100000000000000001 -
b1011 /
b110 ,
b110 +
b11 3
b11000000001000000000000 4
#540
0"
0$
#545
1!
1#
#547
b101 %
b101101010010100000000000000001 '
b1 )
b1100 7
b1100 2
b1100111001110111100000000000 1
#550
0!
0#
#555
1"
1$
#557
b101 3
b101101010010100000000000000001 4
b1 6
b0 0
b111100000000000 .
b1100111001110111100000000000 -
b1100 /
bx ,
bx +
#560
0"
0$
#565
1!
1#
#567
b1101 7
b1101 2
bx %
b1100111001110111100000000000 '
b0 )
#570
0!
0#
#575
1"
1$
#577
b1101 /
bx 3
b1100111001110111100000000000 4
b0 6
#580
0"
0$
#585
1!
1#
#587
b1110 7
b1110 2
b110101010000001111111111111001 1
#590
0!
0#
#595
b0 ,
1"
1$
#597
b100 0
b11111111111111111111111111111001 .
b110101010000001111111111111001 -
b1110 /
b101 +
#600
0"
0$
#605
1!
1#
#607
b1111 7
b1111 2
b100101001000111111111111111110 1
b111 %
b110101010000001111111111111001 '
b100 )
#610
0!
0#
#615
1"
1$
#617
b11 0
b11111111111111111111111111111110 .
b100101001000111111111111111110 -
b1111 /
b11 ,
b11001000 +
b110101010000001111111111111001 4
b100 6
#620
0"
0$
#625
1!
1#
#627
b11 &
b11000110 %
b100101001000111111111111111110 '
b11 )
b1000 7
b1000 2
08
b1000100001100000000000 1
#630
0!
0#
#635
1"
1$
#637
b100101001000111111111111111110 4
b11 6
b0 0
b1100000000000 .
b1000100001100000000000 -
b1000 /
b10 +
#640
0"
0$
#645
1!
1#
#647
b1001 7
b1001 2
b10000000000100000000000 1
b101 %
b1000100001100000000000 '
b0 )
#650
0!
0#
#655
b0 ,
1"
1$
#657
b100000000000 .
b10000000000100000000000 -
b1001 /
b11 +
b101 3
b1000100001100000000000 4
b0 6
#660
0"
0$
#665
1!
1#
#667
b11 %
b10000000000100000000000 '
b1010 7
b1010 2
b11000000001000000000000 1
#670
0!
0#
#675
1"
1$
#677
b11 3
b10000000000100000000000 4
b1000000000000 .
b11000000001000000000000 -
b1010 /
b101 +
#680
0"
0$
#685
1!
1#
#687
b1011 7
b1011 2
b101101010010100000000000000001 1
b101 %
b11000000001000000000000 '
#690
0!
0#
#695
1"
1$
#697
b1 0
b1 .
b101101010010100000000000000001 -
b1011 /
b101 ,
b101 3
b11000000001000000000000 4
#700
0"
0$
#705
1!
1#
#707
b100 %
b101101010010100000000000000001 '
b1 )
b1100 7
b1100 2
b1100111001110111100000000000 1
#710
0!
0#
#715
1"
1$
#717
b100 3
b101101010010100000000000000001 4
b1 6
b0 0
b111100000000000 .
b1100111001110111100000000000 -
b1100 /
bx ,
bx +
#720
0"
0$
#725
1!
1#
#727
b1101 7
b1101 2
bx %
b1100111001110111100000000000 '
b0 )
#730
0!
0#
#735
1"
1$
#737
b1101 /
bx 3
b1100111001110111100000000000 4
b0 6
#740
0"
0$
#745
1!
1#
#747
b1110 7
b1110 2
b110101010000001111111111111001 1
#750
0!
0#
#755
b0 ,
1"
1$
#757
b100 0
b11111111111111111111111111111001 .
b110101010000001111111111111001 -
b1110 /
b100 +
#760
0"
0$
#765
1!
1#
#767
b1111 7
b1111 2
b100101001000111111111111111110 1
b111 %
b110101010000001111111111111001 '
b100 )
#770
0!
0#
#775
1"
1$
#777
b11 0
b11111111111111111111111111111110 .
b100101001000111111111111111110 -
b1111 /
b101 ,
b11001000 +
b110101010000001111111111111001 4
b100 6
#780
0"
0$
#785
1!
1#
#787
b101 &
b11000110 %
b100101001000111111111111111110 '
b11 )
b1000 7
b1000 2
08
b1000100001100000000000 1
#790
0!
0#
#795
1"
1$
#797
b100101001000111111111111111110 4
b11 6
b0 0
b1100000000000 .
b1000100001100000000000 -
b1000 /
b11 +
#800
0"
0$
#805
1!
1#
#807
b1001 7
b1001 2
b10000000000100000000000 1
b1000 %
b1000100001100000000000 '
b0 )
#810
0!
0#
#815
b0 ,
1"
1$
#817
b100000000000 .
b10000000000100000000000 -
b1001 /
b101 +
b1000 3
b1000100001100000000000 4
b0 6
#820
0"
0$
#825
1!
1#
#827
b101 %
b10000000000100000000000 '
b1010 7
b1010 2
b11000000001000000000000 1
#830
0!
0#
#835
1"
1$
#837
b101 3
b10000000000100000000000 4
b1000000000000 .
b11000000001000000000000 -
b1010 /
b1000 +
#840
0"
0$
#845
1!
1#
#847
b1011 7
b1011 2
b101101010010100000000000000001 1
b1000 %
b11000000001000000000000 '
#850
0!
0#
#855
1"
1$
#857
b1 0
b1 .
b101101010010100000000000000001 -
b1011 /
b100 ,
b100 +
b1000 3
b11000000001000000000000 4
#860
0"
0$
#865
1!
1#
#867
b11 %
b101101010010100000000000000001 '
b1 )
b1100 7
b1100 2
b1100111001110111100000000000 1
#870
0!
0#
#875
1"
1$
#877
b11 3
b101101010010100000000000000001 4
b1 6
b0 0
b111100000000000 .
b1100111001110111100000000000 -
b1100 /
bx ,
bx +
#880
0"
0$
#885
1!
1#
#887
b1101 7
b1101 2
bx %
b1100111001110111100000000000 '
b0 )
#890
0!
0#
#895
1"
1$
#897
b1101 /
bx 3
b1100111001110111100000000000 4
b0 6
#900
0"
0$
#905
1!
1#
#907
b1110 7
b1110 2
b110101010000001111111111111001 1
#910
0!
0#
#915
b0 ,
1"
1$
#917
b100 0
b11111111111111111111111111111001 .
b110101010000001111111111111001 -
b1110 /
b11 +
#920
0"
0$
#925
1!
1#
#927
b1111 7
b1111 2
b100101001000111111111111111110 1
b111 %
b110101010000001111111111111001 '
b100 )
#930
0!
0#
#935
1"
1$
#937
b11 0
b11111111111111111111111111111110 .
b100101001000111111111111111110 -
b1111 /
b1000 ,
b11001000 +
b110101010000001111111111111001 4
b100 6
#940
0"
0$
#945
1!
1#
#947
b1000 &
b11000110 %
b100101001000111111111111111110 '
b11 )
b1000 7
b1000 2
08
b1000100001100000000000 1
#950
0!
0#
#955
1"
1$
#957
b100101001000111111111111111110 4
b11 6
b0 0
b1100000000000 .
b1000100001100000000000 -
b1000 /
b101 +
#960
0"
0$
#965
1!
1#
#967
b1001 7
b1001 2
b10000000000100000000000 1
b1101 %
b1000100001100000000000 '
b0 )
#970
0!
0#
#975
b0 ,
1"
1$
#977
b100000000000 .
b10000000000100000000000 -
b1001 /
b1000 +
b1101 3
b1000100001100000000000 4
b0 6
#980
0"
0$
#985
1!
1#
#987
b1000 %
b10000000000100000000000 '
b1010 7
b1010 2
b11000000001000000000000 1
#990
0!
0#
#995
1"
1$
#997
b1000 3
b10000000000100000000000 4
b1000000000000 .
b11000000001000000000000 -
b1010 /
b1101 +
#1000
0"
0$
#1005
1!
1#
#1007
b1011 7
b1011 2
b101101010010100000000000000001 1
b1101 %
b11000000001000000000000 '
#1010
0!
0#
#1015
1"
1$
#1017
b1 0
b1 .
b101101010010100000000000000001 -
b1011 /
b11 ,
b11 +
b1101 3
b11000000001000000000000 4
#1020
0"
0$
#1025
1!
1#
#1027
b10 %
b101101010010100000000000000001 '
b1 )
b1100 7
b1100 2
b1100111001110111100000000000 1
#1030
0!
0#
#1035
1"
1$
#1037
b10 3
b101101010010100000000000000001 4
b1 6
b0 0
b111100000000000 .
b1100111001110111100000000000 -
b1100 /
bx ,
bx +
#1040
0"
0$
#1045
1!
1#
#1047
b1101 7
b1101 2
bx %
b1100111001110111100000000000 '
b0 )
#1050
0!
0#
#1055
1"
1$
#1057
b1101 /
bx 3
b1100111001110111100000000000 4
b0 6
#1060
0"
0$
#1065
1!
1#
#1067
b1110 7
b1110 2
b110101010000001111111111111001 1
#1070
0!
0#
#1075
b0 ,
1"
1$
#1077
b100 0
b11111111111111111111111111111001 .
b110101010000001111111111111001 -
b1110 /
b10 +
#1080
0"
0$
#1085
1!
1#
#1087
b1111 7
b1111 2
b100101001000111111111111111110 1
b111 %
b110101010000001111111111111001 '
b100 )
#1090
0!
0#
#1095
1"
1$
#1097
b11 0
b11111111111111111111111111111110 .
b100101001000111111111111111110 -
b1111 /
b1101 ,
b11001000 +
b110101010000001111111111111001 4
b100 6
#1100
0"
0$
#1105
1!
1#
#1107
b1101 &
b11000110 %
b100101001000111111111111111110 '
b11 )
b1000 7
b1000 2
08
b1000100001100000000000 1
#1110
0!
0#
#1115
1"
1$
#1117
b100101001000111111111111111110 4
b11 6
b0 0
b1100000000000 .
b1000100001100000000000 -
b1000 /
b1000 +
#1120
0"
0$
#1125
1!
1#
#1127
b1001 7
b1001 2
b10000000000100000000000 1
b10101 %
b1000100001100000000000 '
b0 )
#1130
0!
0#
#1135
b0 ,
1"
1$
#1137
b100000000000 .
b10000000000100000000000 -
b1001 /
b1101 +
b10101 3
b1000100001100000000000 4
b0 6
#1140
0"
0$
#1145
1!
1#
#1147
b1101 %
b10000000000100000000000 '
b1010 7
b1010 2
b11000000001000000000000 1
#1150
0!
0#
#1155
1"
1$
#1157
b1101 3
b10000000000100000000000 4
b1000000000000 .
b11000000001000000000000 -
b1010 /
b10101 +
#1160
0"
0$
#1165
1!
1#
#1167
b1011 7
b1011 2
b101101010010100000000000000001 1
b10101 %
b11000000001000000000000 '
#1170
0!
0#
#1175
1"
1$
#1177
b1 0
b1 .
b101101010010100000000000000001 -
b1011 /
b10 ,
b10 +
b10101 3
b11000000001000000000000 4
#1180
0"
0$
#1185
1!
1#
#1187
b1 %
b101101010010100000000000000001 '
b1 )
b1100 7
b1100 2
b1100111001110111100000000000 1
#1190
0!
0#
#1195
1"
1$
#1197
b1 3
b101101010010100000000000000001 4
b1 6
b0 0
b111100000000000 .
b1100111001110111100000000000 -
b1100 /
bx ,
bx +
#1200
0"
0$
#1205
1!
1#
#1207
b1101 7
b1101 2
bx %
b1100111001110111100000000000 '
b0 )
#1210
0!
0#
#1215
1"
1$
#1217
b1101 /
bx 3
b1100111001110111100000000000 4
b0 6
#1220
0"
0$
#1225
1!
1#
#1227
b1110 7
b1110 2
b110101010000001111111111111001 1
#1230
0!
0#
#1235
b0 ,
1"
1$
#1237
b100 0
b11111111111111111111111111111001 .
b110101010000001111111111111001 -
b1110 /
b1 +
#1240
0"
0$
#1245
1!
1#
